timer1101/__init__.py
timer1101/timer.py
timer1101/timerManager.py
timer1101-0.0.3.dist-info/METADATA
timer1101-0.0.3.dist-info/WHEEL
timer1101-0.0.3.dist-info/top_level.txt
timer1101-0.0.3.dist-info/RECORD
