Metadata-Version: 2.1
Name: timer1101
Version: 0.0.3
Summary: A timer for python code
Author-email: Tom <huqh1101@gmail.com>
Maintainer-email: Tom <huqh1101@gmail.com>
License: MIT License
Keywords: timer
Classifier: Development Status :: 3 - Alpha
Classifier: Intended Audience :: Developers
Classifier: Topic :: Software Development
Classifier: License :: OSI Approved :: MIT License
Classifier: Programming Language :: Python :: 3
Classifier: Programming Language :: Python :: 3.10
Requires-Python: >=3.6
Requires-Dist: rs1101
Provides-Extra: test
Requires-Dist: unittest; extra == "test"
